{"cameraMode":{"drawMode":0,"name":"Shaded","section":"Shading Mode"},"sceneLighting":true,"audioPlay":false,"sceneViewState":{"m_AlwaysRefresh":false,"showFog":true,"showSkybox":true,"showFlares":true,"showImageEffects":true,"showParticleSystems":true,"showVisualEffectGraphs":true,"m_FxEnabled":true},"in2DMode":false,"pivot":{"x":0.31363677978515627,"y":10.896760940551758,"z":-8.086978912353516},"rotation":{"x":0.23539139330387116,"y":0.15807205438613892,"z":-0.03883366286754608,"w":0.9581702947616577},"size":10.0,"orthographic":false}